{
    "taskDefinitionArn": "arn:aws:ecs:ap-northeast-2:901512289056:task-definition/final-ecs-task:40",
    "containerDefinitions": [
        {
            "name": "final-test-api",
            "image": "901512289056.dkr.ecr.ap-northeast-2.amazonaws.com/terraform-test:v0.0.3",
            "cpu": 0,
            "portMappings": [
                {
                    "name": "final-test-api-3000-tcp",
                    "containerPort": 3000,
                    "hostPort": 3000,
                    "protocol": "tcp",
                    "appProtocol": "http"
                }
            ],
            "essential": true,
            "environment": [],
            "environmentFiles": [],
            "mountPoints": [],
            "volumesFrom": [],
            "secrets": [
                {
                    "name": "WRITE_HOSTNAME",
                    "valueFrom": "arn:aws:secretsmanager:ap-northeast-2:901512289056:secret:final-terraform/write-endpoint-L3aPig:WRITE_HOSTNAME::"
                },
                {
                    "name": "PASSWORD",
                    "valueFrom": "arn:aws:secretsmanager:ap-northeast-2:901512289056:secret:final-terraform/db-password-kGw9IQ:PASSWORD::"
                },
                {
                    "name": "DATABASE",
                    "valueFrom": "arn:aws:secretsmanager:ap-northeast-2:901512289056:secret:final-terraform/db-database-aO78UY:DATABASE::"
                },
                {
                    "name": "READ_HOSTNAME",
                    "valueFrom": "arn:aws:secretsmanager:ap-northeast-2:901512289056:secret:final-terraform/readendpoint-beXGUg:READ_HOSTNAME::"
                },
                {
                    "name": "USERNAME",
                    "valueFrom": "arn:aws:secretsmanager:ap-northeast-2:901512289056:secret:final-terraform/db-username-gIDG8o:USERNAME::"
                },
                {
                    "name": "AWS_ACCESS_KEY_ID",
                    "valueFrom": "arn:aws:secretsmanager:ap-northeast-2:901512289056:secret:final-terraform/aws-access-key-id-k6JaE2"
                },
                {
                    "name": "AWS_SECRET_ACCESS_KEY",
                    "valueFrom": "arn:aws:secretsmanager:ap-northeast-2:901512289056:secret:final-terraform/aws-secret-access-key-uNFoT5"
                }
            ],
            "logConfiguration": {
                "logDriver": "awslogs",
                "options": {
                    "awslogs-create-group": "true",
                    "awslogs-group": "/ecs/test/example",
                    "awslogs-region": "ap-northeast-2",
                    "awslogs-stream-prefix": "ecs"
                }
            }
        }
    ],
    "family": "final-ecs-task",
    "executionRoleArn": "arn:aws:iam::901512289056:role/ecs-task-execution-role",
    "networkMode": "awsvpc",
    "revision": 40,
    "volumes": [],
    "status": "ACTIVE",
    "requiresAttributes": [
        {
            "name": "com.amazonaws.ecs.capability.logging-driver.awslogs"
        },
        {
            "name": "ecs.capability.execution-role-awslogs"
        },
        {
            "name": "com.amazonaws.ecs.capability.ecr-auth"
        },
        {
            "name": "com.amazonaws.ecs.capability.docker-remote-api.1.19"
        },
        {
            "name": "ecs.capability.secrets.asm.environment-variables"
        },
        {
            "name": "ecs.capability.execution-role-ecr-pull"
        },
        {
            "name": "com.amazonaws.ecs.capability.docker-remote-api.1.18"
        },
        {
            "name": "ecs.capability.task-eni"
        },
        {
            "name": "com.amazonaws.ecs.capability.docker-remote-api.1.29"
        }
    ],
    "placementConstraints": [],
    "compatibilities": [
        "EC2",
        "FARGATE"
    ],
    "requiresCompatibilities": [
        "FARGATE"
    ],
    "cpu": "512",
    "memory": "1024",
    "registeredAt": "2023-03-21T01:14:31.038Z",
    "registeredBy": "arn:aws:iam::901512289056:user/minhyeok",
    "tags": []
}